rtl/reg_file.sv
module reg_file (
    input  logic        clk,
    input  logic        rst_n,
    input  logic [4:0]  rs1_addr,
    input  logic [4:0]  rs2_addr,
    input  logic [4:0]  rd_addr,
    input  logic [31:0] rd_data_in,
    input  logic        reg_write,
    output logic [31:0] rs1_data,
    output logic [31:0] rs2_data
);
    logic [31:0] registers [31:0];
    integer      index;

    always_ff @(posedge clk or negedge rst_n) begin
        if (!rst_n) begin
            for (index = 0; index < 32; index = index + 1) begin
                registers[index] <= 32'h0000_0000;
            end
        end else begin
            if (reg_write && (rd_addr != 5'd0)) begin
                registers[rd_addr] <= rd_data_in;
            end
        end
    end

    always_comb begin
        rs1_data = 32'h0000_0000;
        rs2_data = 32'h0000_0000;

        if (rst_n) begin
            if (rs1_addr == 5'd0) begin
                rs1_data = 32'h0000_0000;
            end else if (reg_write && (rd_addr == rs1_addr) && (rd_addr != 5'd0)) begin
                rs1_data = rd_data_in;
            end else begin
                rs1_data = registers[rs1_addr];
            end

            if (rs2_addr == 5'd0) begin
                rs2_data = 32'h0000_0000;
            end else if (reg_write && (rd_addr == rs2_addr) && (rd_addr != 5'd0)) begin
                rs2_data = rd_data_in;
            end else begin
                rs2_data = registers[rs2_addr];
            end
        end
    end
endmodule

tb/reg_file_tb.sv
module reg_file_tb;
    logic        clk;
    logic        rst_n;
    logic [4:0]  rs1_addr;
    logic [4:0]  rs2_addr;
    logic [4:0]  rd_addr;
    logic [31:0] rd_data_in;
    logic        reg_write;
    logic [31:0] rs1_data;
    logic [31:0] rs2_data;

    reg_file dut (
        .clk(clk),
        .rst_n(rst_n),
        .rs1_addr(rs1_addr),
        .rs2_addr(rs2_addr),
        .rd_addr(rd_addr),
        .rd_data_in(rd_data_in),
        .reg_write(reg_write),
        .rs1_data(rs1_data),
        .rs2_data(rs2_data)
    );

    always #5 clk = ~clk;

    task automatic check_read(
        input logic [31:0] expected_rs1,
        input logic [31:0] expected_rs2,
        input string       test_name
    );
        begin
            #1;
            if (rs1_data !== expected_rs1 || rs2_data !== expected_rs2) begin
                $display("FAIL: %s | expected rs1=%h rs2=%h, got rs1=%h rs2=%h", test_name, expected_rs1, expected_rs2, rs1_data, rs2_data);
                $fatal(1);
            end
            $display("PASS: %s", test_name);
        end
    endtask

    initial begin
        $dumpfile("dump.vcd");
        $dumpvars(0, reg_file_tb);

        clk = 1'b0;
        rst_n = 1'b0;
        rs1_addr = 5'd0;
        rs2_addr = 5'd0;
        rd_addr = 5'd0;
        rd_data_in = 32'h0000_0000;
        reg_write = 1'b0;

        #12;
        rst_n = 1'b1;
        #1;
        check_read(32'h0000_0000, 32'h0000_0000, "Reset clears reads to zero");

        rs1_addr = 5'd0;
        rs2_addr = 5'd0;
        rd_addr = 5'd1;
        rd_data_in = 32'h1234_5678;
        reg_write = 1'b1;
        #1;
        check_read(32'h0000_0000, 32'h0000_0000, "X0 remains zero during write enable");
        @(posedge clk);
        #1;

        reg_write = 1'b0;
        rs1_addr = 5'd1;
        rs2_addr = 5'd0;
        #1;
        check_read(32'h1234_5678, 32'h0000_0000, "Written register reads back");

        rd_addr = 5'd2;
        rd_data_in = 32'hDEAD_BEEF;
        reg_write = 1'b1;
        rs1_addr = 5'd2;
        rs2_addr = 5'd1;
        #1;
        check_read(32'hDEAD_BEEF, 32'h1234_5678, "Same-cycle bypass on read ports");
        @(posedge clk);
        #1;

        reg_write = 1'b0;
        rs1_addr = 5'd2;
        rs2_addr = 5'd1;
        #1;
        check_read(32'hDEAD_BEEF, 32'h1234_5678, "Stored values persist after write clock");

        rst_n = 1'b0;
        #1;
        check_read(32'h0000_0000, 32'h0000_0000, "Async reset clears outputs");

        $display("All register file tests passed.");
        $finish;
    end
endmodule

sim/dump.vcd
$date
	Tue Jun 23 20:29:10 2026
$end
$version
	Icarus Verilog
$end
$timescale
	1s
$end
$scope module reg_file_tb $end
$var wire 32 ! rs2_data [31:0] $end
$var wire 32 " rs1_data [31:0] $end
$var reg 1 # clk $end
$var reg 5 $ rd_addr [4:0] $end
$var reg 32 % rd_data_in [31:0] $end
$var reg 1 & reg_write $end
$var reg 5 ' rs1_addr [4:0] $end
$var reg 5 ( rs2_addr [4:0] $end
$var reg 1 ) rst_n $end
$scope module dut $end
$var wire 1 # clk $end
$var wire 5 * rd_addr [4:0] $end
$var wire 32 + rd_data_in [31:0] $end
$var wire 1 & reg_write $end
$var wire 5 , rs1_addr [4:0] $end
$var wire 5 - rs2_addr [4:0] $end
$var wire 1 ) rst_n $end
$var reg 32 . rs1_data [31:0] $end
$var reg 32 / rs2_data [31:0] $end
$var integer 32 0 index [31:0] $end
$upscope $end
$scope task check_read $end
$upscope $end
$upscope $end
$enddefinitions $end
$comment Show the parameter values. $end
$dumpall
$end
#0
$dumpvars
b100000 0
b0 /
b0 .
b0 -
b0 ,
b0 +
b0 *
0)
b0 (
b0 '
0&
b0 %
b0 $
0#
b0 "
b0 !
$end
#5
b100000 0
1#
#10
0#
#12
1)
#14
1&
b10010001101000101011001111000 %
b10010001101000101011001111000 +
b1 $
b1 *
#15
1#
#20
0#
#25
1#
#26
b10010001101000101011001111000 "
b10010001101000101011001111000 .
b1 '
b1 ,
0&
#28
b10010001101000101011001111000 !
b10010001101000101011001111000 /
b11011110101011011011111011101111 "
b11011110101011011011111011101111 .
b1 (
b1 -
b10 '
b10 ,
1&
b11011110101011011011111011101111 %
b11011110101011011011111011101111 +
b10 $
b10 *
#30
0#
#35
b10010001101000101011001111000 !
b10010001101000101011001111000 /
b11011110101011011011111011101111 "
b11011110101011011011111011101111 .
1#
#36
b10010001101000101011001111000 !
b10010001101000101011001111000 /
b11011110101011011011111011101111 "
b11011110101011011011111011101111 .
0&
#38
b0 !
b0 /
b0 "
b0 .
b100000 0
0)
